vault_ssh_renew/__init__.py
vault_ssh_renew/cert.py
vault_ssh_renew/cli.py
vault_ssh_renew/config.py
vault_ssh_renew/errors.py
vault_ssh_renew/util.py
vault_ssh_renew/vault.py
vault_ssh_renew-0.2.0.dist-info/entry_points.txt
vault_ssh_renew-0.2.0.dist-info/LICENSE
vault_ssh_renew-0.2.0.dist-info/WHEEL
vault_ssh_renew-0.2.0.dist-info/METADATA
vault_ssh_renew-0.2.0.dist-info/RECORD
