Metadata-Version: 2.1
Name: vault-ssh-renew
Version: 0.2.0
Summary: Vault SSH Host Key Renewal Tool
Home-page: https://github.com/ngrewe/vault-ssh-renew
License: MIT
Author: Niels Grewe
Author-email: niels.grewe@halbordnung.de
Requires-Python: >=3.6,<4.0
Classifier: License :: OSI Approved :: MIT License
Classifier: Programming Language :: Python :: 3
Classifier: Programming Language :: Python :: 3.6
Classifier: Programming Language :: Python :: 3.7
Classifier: Programming Language :: Python :: 3.8
Requires-Dist: click (>=6.6,<7.0)
Requires-Dist: paramiko (>=2.7.1,<3.0.0)
Requires-Dist: requests (>=2.12.4,<3.0.0)
